{"cameraMode":{"drawMode":0,"name":"Shaded","section":"Shading Mode"},"sceneLighting":true,"audioPlay":false,"sceneViewState":{"m_AlwaysRefresh":false,"showFog":true,"showSkybox":true,"showFlares":true,"showImageEffects":true,"showParticleSystems":true,"showVisualEffectGraphs":true,"m_FxEnabled":true},"in2DMode":false,"pivot":{"x":-16.115575790405275,"y":0.9594957232475281,"z":-10.228118896484375},"rotation":{"x":-0.03452271223068237,"y":0.8812410831451416,"z":-0.06516241282224655,"w":-0.46687787771224978},"size":10.0,"orthographic":false}